michen00/__init__.py
michen00/core.py
michen00-0.0.0.dist-info/METADATA
michen00-0.0.0.dist-info/WHEEL
michen00-0.0.0.dist-info/top_level.txt
michen00-0.0.0.dist-info/RECORD
